pytorch_smartcrop/__init__.py
pytorch_smartcrop/smartcrop.py
pytorch_smartcrop-1.0.0.dist-info/LICENSE
pytorch_smartcrop-1.0.0.dist-info/METADATA
pytorch_smartcrop-1.0.0.dist-info/WHEEL
pytorch_smartcrop-1.0.0.dist-info/top_level.txt
pytorch_smartcrop-1.0.0.dist-info/RECORD
