Metadata-Version: 2.1
Name: pytorch-smartcrop
Version: 1.0.0
Summary: Smartcrop transform for PyTorch
Author-email: Michał Dyczko <michal@dyczko.dev>
License: MIT License
Project-URL: Homepage, https://github.com/michaldyczko/pytorch-smartcrop
Keywords: pytorch,smartcrop,image,transform
Requires-Python: >=3.8
License-File: LICENSE
Requires-Dist: torch >=2.2.1
Requires-Dist: Pillow
Requires-Dist: pyvips >=2.2.2
